{
  "format_version": "1.8.0",
  "animations": {
    "skeleton_vanguard_idle": {
      "loop": true,
      "bones": {
        "bipedLegLeft": {
          "rotation": {
            "vector": [9.99527, 0.21782, -2.4905]
          }
        },
        "bipedLegRight": {
          "rotation": {
            "vector": [-15, 0, 0]
          },
          "position": {
            "vector": [0, -0.2, -0.5]
          }
        },
        "bipedBody": {
          "rotation": {
            "vector": ["17.5+Math.cos(query.life_time * (1 * 150)) * (1 * 2)", 0, 0]
          }
        },
        "bipedArmLeft": {
          "rotation": {
            "vector": ["38.1363+Math.cos(query.life_time * (1 * 150) + 25) * (1 * 2)", 12.12312, -19.00709]
          },
          "position": {
            "vector": [0, 0, 0.5]
          }
        },
        "bipedHandLeft": {
          "rotation": {
            "vector": [-47.30905, -1.68575, 1.8335]
          }
        },
        "bipedArmRight": {
          "rotation": {
            "vector": [
              "-97.455+Math.cos(query.life_time * (1 * 150) + 25) * (1 * 2)", 7.5496,
              "0.1067+Math.cos(query.life_time * (1 * 150) + 25) * (1 * 2)"
            ]
          }
        },
        "bipedHandRight": {
          "rotation": {
            "vector": [357.51919, 7.05906, "169.6851 + 180"]
          },
          "position": {
            "vector": [1, 2, 4]
          }
        },
        "bipedHead": {
          "rotation": {
            "vector": ["-15+Math.cos(query.life_time * (1 * 150) + 25) * (1 * -1.5)", 0, 0]
          }
        }
      }
    },
    "skeleton_vanguard_blocking": {
      "loop": true,
      "bones": {
        "bipedLegLeft": {
          "rotation": {
            "vector": [7.49527, 0.21782, -2.4905]
          }
        },
        "bipedLegRight": {
          "rotation": {
            "vector": [-7.49294, 0.32621, 2.47864]
          },
          "position": {
            "vector": [0, -0.2, -0.5]
          }
        },
        "bipedBody": {
          "rotation": {
            "vector": ["12.5+Math.cos(query.life_time * (1 * 150)) * (1 * 2)", 0, 0]
          }
        },
        "bipedArmLeft": {
          "rotation": {
            "vector": ["-61.169+Math.cos(query.life_time * (1 * 150)) * (1 * -2)", -14.51824, 0.91798]
          },
          "position": {
            "vector": [0, 0, "0.5+Math.cos(query.life_time * (1 * 150)) * (1 * 0.25)"]
          }
        },
        "bipedHandLeft": {
          "rotation": {
            "vector": [-37.30905, -1.68575, 1.8335]
          }
        },
        "bipedArmRight": {
          "rotation": {
            "vector": [
              "-84.9902+Math.cos(query.life_time * (1 * 150) + 50) * (1 * 1)", -9.8664,
              "1.8263+Math.cos(query.life_time * (1 * 150) + 25) * (1 * 2)"
            ]
          }
        },
        "bipedHandRight": {
          "rotation": {
            "vector": [333.11109, -20.00909, "216.5066 + 180"]
          }
        },
        "bipedHead": {
          "rotation": {
            "vector": ["-10+Math.cos(query.life_time * (1 * 150) + 25) * (1 * -1.5)", 0, 0]
          }
        }
      }
    },
    "skeleton_vanguard_walk": {
      "loop": true,
      "bones": {
        "bipedLegLeft": {
          "rotation": {
            "vector": ["Math.cos(query.life_time * (query.ground_speed * 300)) * (1 * -17.5)", 2.22526, 0]
          },
          "position": {
            "vector": [
              0, "Math.clamp(Math.cos(query.life_time * (query.ground_speed * 300) + 50) * (1 * 3), -0.25, 360)",
              "Math.cos(query.life_time * (query.ground_speed * 300) + 25) * (1 * -1)"
            ]
          }
        },
        "bipedLegRight": {
          "rotation": {
            "vector": ["Math.cos(query.life_time * (query.ground_speed * 300)) * (1 * 17.5)", -2.2253, 0]
          },
          "position": {
            "vector": [
              0, "-Math.clamp(Math.cos(query.life_time * (query.ground_speed * 300) + 50) * (1 * 3), -360, 0.25)",
              "-Math.cos(query.life_time * (query.ground_speed * 300) + 25) * (1 * -1)"
            ]
          }
        },
        "bipedBody": {
          "rotation": {
            "vector": ["17.5+Math.cos(query.life_time * (query.ground_speed * 600)) * (1 * 2)", 0, 0]
          },
          "position": {
            "vector": [
              0,
              "-0.25+Math.clamp(Math.cos(query.life_time * (query.ground_speed * 600) + 50) * (1 * 0.5), -0.25, 360)",
              -0.25
            ]
          }
        },
        "bipedArmLeft": {
          "rotation": {
            "vector": [
              "38.1363+Math.cos(query.life_time * (query.ground_speed * 600) + 25) * (1 * 2)", 12.12312, -19.00709
            ]
          },
          "position": {
            "vector": [0, 0, 0.5]
          }
        },
        "bipedHandLeft": {
          "rotation": {
            "vector": [-47.30905, -1.68575, 1.8335]
          }
        },
        "bipedArmRight": {
          "rotation": {
            "vector": [
              "-97.455+Math.cos(query.life_time * (query.ground_speed * 600) + 25) * (1 * 2)", 7.5496,
              "0.1067+Math.cos(query.life_time * (query.ground_speed * 150) + 25) * (1 * 2)"
            ]
          }
        },
        "bipedHandRight": {
          "rotation": {
            "vector": [357.51919, 7.05906, "169.6851 + 180"]
          },
          "position": {
            "vector": [1, 2, 4]
          }
        },
        "bipedHead": {
          "rotation": {
            "vector": ["-15+Math.cos(query.life_time * (query.ground_speed * 600) + 25) * (1 * -1.5)", 0, 0]
          }
        }
      }
    },
    "skeleton_vanguard_walk_blocking": {
      "loop": true,
      "bones": {
        "bipedLegLeft": {
          "rotation": {
            "vector": ["Math.cos(query.life_time * (query.ground_speed * 300)) * (1 * -17.5)", 2.22526, 0]
          },
          "position": {
            "vector": [
              0, "Math.clamp(Math.cos(query.life_time * (query.ground_speed * 300) + 50) * (1 * 3), -0.25, 360)",
              "Math.cos(query.life_time * (query.ground_speed * 300) + 25) * (1 * -1)"
            ]
          }
        },
        "bipedLegRight": {
          "rotation": {
            "vector": ["Math.cos(query.life_time * (query.ground_speed * 300)) * (1 * 17.5)", -2.2253, 0]
          },
          "position": {
            "vector": [
              0, "-Math.clamp(Math.cos(query.life_time * (query.ground_speed * 300) + 50) * (1 * 3), -360, 0.25)",
              "-Math.cos(query.life_time * (query.ground_speed * 300) + 25) * (1 * -1)"
            ]
          }
        },
        "bipedBody": {
          "rotation": {
            "vector": ["17.5+Math.cos(query.life_time * (query.ground_speed * 600)) * (1 * 2)", 0, 0]
          },
          "position": {
            "vector": [
              0,
              "-0.25+Math.clamp(Math.cos(query.life_time * (query.ground_speed * 600) + 50) * (1 * 0.5), -0.25, 360)",
              -0.25
            ]
          }
        },
        "bipedArmLeft": {
          "rotation": {
            "vector": [
              "-67.6516+Math.cos(query.life_time * (query.ground_speed * 300)) * (1 * -5)", -24.09184, -2.14803
            ]
          },
          "position": {
            "vector": [0, 0, "0.5+Math.cos(query.life_time * (query.ground_speed * 300)) * (1 * 0.25)"]
          }
        },
        "bipedHandLeft": {
          "rotation": {
            "vector": [-37.30905, -1.68575, 1.8335]
          }
        },
        "bipedArmRight": {
          "rotation": {
            "vector": [
              "-84.9902+Math.cos(query.life_time * (query.ground_speed * 300) + 50) * (1 * 1)", -9.8664,
              "1.8263+Math.cos(query.life_time * (query.ground_speed * 300) + 25) * (1 * 2)"
            ]
          }
        },
        "bipedHandRight": {
          "rotation": {
            "vector": [333.11109, -20.00909, "216.5066 + 180"]
          }
        },
        "bipedHead": {
          "rotation": {
            "vector": ["-15+Math.cos(query.life_time * (query.ground_speed * 600) + 25) * (1 * -1.5)", 0, 0]
          }
        }
      }
    },
    "skeleton_vanguard_attack": {
      "loop": "hold_on_last_frame",
      "animation_length": 1.125,
      "bones": {
        "bipedLegLeft": {
          "rotation": {
            "vector": [9.99527, 0.21782, -2.4905]
          }
        },
        "bipedLegRight": {
          "rotation": {
            "vector": [-15, 0, 0]
          },
          "position": {
            "vector": [0, -0.2, -0.5]
          }
        },
        "bipedBody": {
          "rotation": {
            "0.0": {
              "vector": ["17.5+Math.cos(query.life_time * (1 * 150)) * (1 * 2)", 0, 0]
            },
            "0.25": {
              "vector": ["9.8975+Math.cos(query.life_time * (1 * 150)) * (1 * 2)", -3.04115, 1.80292],
              "easing": "easeInOutSine"
            },
            "0.5": {
              "vector": ["27.3975+Math.cos(query.life_time * (1 * 150)) * (1 * 2)", 0, 0],
              "easing": "easeInOutSine"
            },
            "0.7917": {
              "vector": ["17.5+Math.cos(query.life_time * (1 * 150)) * (1 * 2)", 0, 0],
              "easing": "easeInOutSine"
            }
          }
        },
        "bipedArmLeft": {
          "rotation": {
            "0.0": {
              "vector": ["38.1363+Math.cos(query.life_time * (1 * 150) + 25) * (1 * 2)", 12.12312, -19.00709]
            },
            "0.4583": {
              "vector": ["52.7561+Math.cos(query.life_time * (1 * 150) + 25) * (1 * 2)", 14.00855, -20.69172],
              "easing": "easeInOutSine"
            },
            "0.6667": {
              "vector": ["-72.2536+Math.cos(query.life_time * (1 * 150) + 25) * (1 * 2)", 5.66733, -12.18828],
              "easing": "easeInOutSine"
            },
            "0.8333": {
              "vector": ["-72.2536+Math.cos(query.life_time * (1 * 150) + 25) * (1 * 2)", 5.66733, -12.18828],
              "easing": "easeInOutSine"
            },
            "1.125": {
              "vector": ["38.1363+Math.cos(query.life_time * (1 * 150) + 25) * (1 * 2)", 12.12312, -19.00709],
              "easing": "easeInOutSine"
            }
          },
          "position": {
            "0.0": {
              "vector": [0, 0, 0.5]
            },
            "0.4583": {
              "vector": [0, 0, 0.75],
              "easing": "easeInOutSine"
            },
            "0.75": {
              "vector": [0, 0, -2.25],
              "easing": "easeInOutSine"
            },
            "1.125": {
              "vector": [0, 0, 0.5],
              "easing": "easeInOutSine"
            }
          }
        },
        "bipedHandLeft": {
          "rotation": {
            "0.0": {
              "vector": [-47.30905, -1.68575, 1.8335]
            },
            "0.2083": {
              "vector": [-47.31, -1.69, 1.83]
            },
            "0.5": {
              "vector": [56.23402, -0.50116, 0.91185],
              "easing": "easeInOutSine"
            }
          }
        },
        "bipedArmRight": {
          "rotation": {
            "0.0": {
              "vector": [
                "-38.858+Math.cos(query.life_time * (1 * 150) + 25) * (1 * 2)", 10.12966,
                "7.2344+Math.cos(query.life_time * (1 * 150) + 25) * (1 * 2)"
              ]
            },
            "0.4167": {
              "vector": [
                "-38.858+Math.cos(query.life_time * (1 * 150) + 25) * (1 * 2)", 10.12966,
                "7.2344+Math.cos(query.life_time * (1 * 150) + 25) * (1 * 2)"
              ]
            }
          }
        },
        "bipedHandRight": {
          "rotation": {
            "vector": [366.8258, 3.06702, "255.0207 + 180"]
          },
          "position": {
            "vector": [3, 2, 4]
          }
        },
        "bipedHead": {
          "rotation": {
            "0.0417": {
              "vector": ["-15+Math.cos(query.life_time * (1 * 150) + 25) * (1 * -1.5)", 0, 0]
            },
            "0.2917": {
              "vector": ["-5+Math.cos(query.life_time * (1 * 150) + 25) * (1 * -1.5)", 0, 0],
              "easing": "easeInOutSine"
            },
            "0.5": {
              "vector": ["-25+Math.cos(query.life_time * (1 * 150) + 25) * (1 * -1.5)", 0, 0],
              "easing": "easeInOutSine"
            },
            "0.875": {
              "vector": ["-15+Math.cos(query.life_time * (1 * 150) + 25) * (1 * -1.5)", 0, 0],
              "easing": "easeInOutSine"
            }
          }
        }
      }
    },
    "skeleton_vanguard_new_idle": {
      "loop": true,
      "bones": {
        "bipedLegLeft": {
          "rotation": {
            "vector": [9.99527, 0.21782, -2.4905]
          }
        },
        "bipedLegRight": {
          "rotation": {
            "vector": [-15, 0, 0]
          },
          "position": {
            "vector": [0, -0.2, -0.5]
          }
        },
        "bipedBody": {
          "rotation": {
            "vector": ["17.5+Math.cos(query.life_time * (1 * 150)) * (1 * 2)", 0, 0]
          }
        },
        "bipedArmLeft": {
          "rotation": {
            "vector": ["23.1363+Math.cos(query.life_time * (1 * 150) + 25) * (1 * 2)", 12.12312, -19.00709]
          },
          "position": {
            "vector": [0, 0, 0.5]
          }
        },
        "bipedHandLeft": {
          "rotation": {
            "vector": [-47.30905, -1.68575, 1.8335]
          }
        },
        "bipedArmRight": {
          "rotation": {
            "vector": [
              "-38.858+Math.cos(query.life_time * (1 * 150) + 25) * (1 * 2)", 10.12966,
              "7.2344+Math.cos(query.life_time * (1 * 150) + 25) * (1 * 2)"
            ]
          }
        },
        "bipedHandRight": {
          "rotation": {
            "vector": [366.8258, 3.06702, "255.0207 + 180"]
          },
          "position": {
            "vector": [3, 2, 4]
          }
        },
        "bipedHead": {
          "rotation": {
            "vector": ["-15+Math.cos(query.life_time * (1 * 150) + 25) * (1 * -1.5)", 0, 0]
          }
        }
      }
    },
    "skeleton_vanguard_new_blocking": {
      "loop": true,
      "bones": {
        "bipedLegLeft": {
          "rotation": {
            "vector": [9.99527, 0.21782, -2.4905]
          }
        },
        "bipedLegRight": {
          "rotation": {
            "vector": [-15, 0, 0]
          },
          "position": {
            "vector": [0, -0.2, -0.5]
          }
        },
        "bipedBody": {
          "rotation": {
            "vector": ["17.5+Math.cos(query.life_time * (1 * 150)) * (1 * 2)", 0, 0]
          }
        },
        "bipedArmLeft": {
          "rotation": {
            "vector": ["38.1363+Math.cos(query.life_time * (1 * 150) + 25) * (1 * 2)", 12.12312, -19.00709]
          },
          "position": {
            "vector": [0, 0, 0.5]
          }
        },
        "bipedHandLeft": {
          "rotation": {
            "vector": [-47.30905, -1.68575, 1.8335]
          }
        },
        "bipedArmRight": {
          "rotation": {
            "vector": [
              "-97.455+Math.cos(query.life_time * (1 * 150) + 25) * (1 * 2)", 7.5496,
              "0.1067+Math.cos(query.life_time * (1 * 150) + 25) * (1 * 2)"
            ]
          }
        },
        "bipedHandRight": {
          "rotation": {
            "vector": [353.32418, -39.40487, "198.0167 + 180"]
          },
          "position": {
            "vector": [1, 2, 4]
          }
        },
        "bipedHead": {
          "rotation": {
            "vector": ["-15+Math.cos(query.life_time * (1 * 150) + 25) * (1 * -1.5)", 0, 0]
          }
        }
      }
    },
    "skeleton_vanguard_new_walk": {
      "loop": true,
      "bones": {
        "bipedLegLeft": {
          "rotation": {
            "vector": ["Math.cos(query.life_time * (query.ground_speed * 300)) * (1 * -17.5)", 2.22526, 0]
          },
          "position": {
            "vector": [
              0, "Math.clamp(Math.cos(query.life_time * (query.ground_speed * 300) + 50) * (1 * 3), -0.25, 360)",
              "Math.cos(query.life_time * (query.ground_speed * 300) + 25) * (1 * -1)"
            ]
          }
        },
        "bipedLegRight": {
          "rotation": {
            "vector": ["Math.cos(query.life_time * (query.ground_speed * 300)) * (1 * 17.5)", -2.2253, 0]
          },
          "position": {
            "vector": [
              0, "-Math.clamp(Math.cos(query.life_time * (query.ground_speed * 300) + 50) * (1 * 3), -360, 0.25)",
              "-Math.cos(query.life_time * (query.ground_speed * 300) + 25) * (1 * -1)"
            ]
          }
        },
        "bipedBody": {
          "rotation": {
            "vector": ["17.5+Math.cos(query.life_time * (query.ground_speed * 600)) * (1 * 2)", 0, 0]
          },
          "position": {
            "vector": [
              0,
              "-0.25+Math.clamp(Math.cos(query.life_time * (query.ground_speed * 600) + 50) * (1 * 0.5), -0.25, 360)",
              -0.25
            ]
          }
        },
        "bipedArmLeft": {
          "rotation": {
            "vector": [
              "23.1363+Math.cos(query.life_time * (query.ground_speed * 600) + 25) * (1 * 2)", 12.12312, -19.00709
            ]
          },
          "position": {
            "vector": [0, 0, 0.5]
          }
        },
        "bipedHandLeft": {
          "rotation": {
            "vector": [-47.30905, -1.68575, 1.8335]
          }
        },
        "bipedArmRight": {
          "rotation": {
            "vector": [
              "-38.858+Math.cos(query.life_time * (query.ground_speed * 600) + 25) * (1 * 2)", 10.12966,
              "7.2344+Math.cos(query.life_time * (query.ground_speed * 150) + 25) * (1 * 2)"
            ]
          }
        },
        "bipedHandRight": {
          "rotation": {
            "vector": [366.8258, 3.06702, "255.0207 + 180"]
          },
          "position": {
            "vector": [3, 2, 4]
          }
        },
        "bipedHead": {
          "rotation": {
            "vector": ["-15+Math.cos(query.life_time * (query.ground_speed * 600) + 25) * (1 * -1.5)", 0, 0]
          }
        }
      }
    },
    "skeleton_vanguard_new_walk_blocking": {
      "loop": true,
      "bones": {
        "bipedLegLeft": {
          "rotation": {
            "vector": ["Math.cos(query.life_time * (query.ground_speed * 300)) * (1 * -17.5)", 2.22526, 0]
          },
          "position": {
            "vector": [
              0, "Math.clamp(Math.cos(query.life_time * (query.ground_speed * 300) + 50) * (1 * 3), -0.25, 360)",
              "Math.cos(query.life_time * (query.ground_speed * 300) + 25) * (1 * -1)"
            ]
          }
        },
        "bipedLegRight": {
          "rotation": {
            "vector": ["Math.cos(query.life_time * (query.ground_speed * 300)) * (1 * 17.5)", -2.2253, 0]
          },
          "position": {
            "vector": [
              0, "-Math.clamp(Math.cos(query.life_time * (query.ground_speed * 300) + 50) * (1 * 3), -360, 0.25)",
              "-Math.cos(query.life_time * (query.ground_speed * 300) + 25) * (1 * -1)"
            ]
          }
        },
        "bipedBody": {
          "rotation": {
            "vector": ["17.5+Math.cos(query.life_time * (query.ground_speed * 600)) * (1 * 2)", 0, 0]
          },
          "position": {
            "vector": [
              0,
              "-0.25+Math.clamp(Math.cos(query.life_time * (query.ground_speed * 600) + 50) * (1 * 0.5), -0.25, 360)",
              -0.25
            ]
          }
        },
        "bipedArmLeft": {
          "rotation": {
            "vector": [
              "38.1363+Math.cos(query.life_time * (query.ground_speed * 600) + 25) * (1 * 2)", 12.12312, -19.00709
            ]
          },
          "position": {
            "vector": [0, 0, 0.5]
          }
        },
        "bipedHandLeft": {
          "rotation": {
            "vector": [-47.30905, -1.68575, 1.8335]
          }
        },
        "bipedArmRight": {
          "rotation": {
            "vector": [
              "-97.455+Math.cos(query.life_time * (query.ground_speed * 600) + 25) * (1 * 2)", 7.5496,
              "0.1067+Math.cos(query.life_time * (query.ground_speed * 150) + 25) * (1 * 2)"
            ]
          }
        },
        "bipedHandRight": {
          "rotation": {
            "vector": [353.32418, -39.40487, "198.0167 + 180"]
          },
          "position": {
            "vector": [1, 2, 4]
          }
        },
        "bipedHead": {
          "rotation": {
            "vector": ["-15+Math.cos(query.life_time * (query.ground_speed * 600) + 25) * (1 * -1.5)", 0, 0]
          }
        }
      }
    }
  },
  "geckolib_format_version": 2
}